retriever/__init__.py
retriever/__main__.py
retriever/_version.py
retriever/compile.py
retriever/lscolumns.py
retriever/term_size.py
retriever/try_install_all.py
retriever/engines/__init__.py
retriever/engines/csvengine.py
retriever/engines/download_only.py
retriever/engines/hdf5.py
retriever/engines/jsonengine.py
retriever/engines/msaccess.py
retriever/engines/mysql.py
retriever/engines/postgres.py
retriever/engines/sqlite.py
retriever/engines/xmlengine.py
retriever/lib/__init__.py
retriever/lib/cleanup.py
retriever/lib/create_scripts.py
retriever/lib/datapackage.py
retriever/lib/datasets.py
retriever/lib/defaults.py
retriever/lib/download.py
retriever/lib/dummy.py
retriever/lib/engine.py
retriever/lib/engine_tools.py
retriever/lib/excel.py
retriever/lib/fetch.py
retriever/lib/get_opts.py
retriever/lib/install.py
retriever/lib/load_json.py
retriever/lib/models.py
retriever/lib/provenance.py
retriever/lib/provenance_tools.py
retriever/lib/rdatasets.py
retriever/lib/repository.py
retriever/lib/scripts.py
retriever/lib/socrata.py
retriever/lib/table.py
retriever/lib/templates.py
retriever/lib/tools.py
retriever/lib/warning.py
retriever-3.1.0.data/data/CITATION
retriever-3.1.0.dist-info/LICENSE
retriever-3.1.0.dist-info/METADATA
retriever-3.1.0.dist-info/WHEEL
retriever-3.1.0.dist-info/entry_points.txt
retriever-3.1.0.dist-info/top_level.txt
retriever-3.1.0.dist-info/RECORD
