Metadata-Version: 2.1
Name: retriever
Version: 3.1.0
Summary: Data Retriever
Home-page: https://github.com/weecology/retriever
Author: Ben Morris, Shivam Negi, Akash Goel, Andrew Zhang, Henry Senyondo, Ethan White
Author-email: ethan@weecology.org
License: UNKNOWN
Platform: UNKNOWN
Classifier: Intended Audience :: Science/Research
Classifier: License :: OSI Approved :: MIT License
Classifier: Operating System :: Microsoft :: Windows
Classifier: Operating System :: POSIX
Classifier: Operating System :: Unix
Classifier: Programming Language :: Python
Classifier: Programming Language :: Python :: 3
Classifier: Programming Language :: Python :: 3.4
Classifier: Programming Language :: Python :: 3.5
Classifier: Programming Language :: Python :: 3.6
Classifier: Programming Language :: Python :: 3.7
Classifier: Programming Language :: Python :: Implementation :: PyPy
Classifier: Topic :: Software Development :: Libraries :: Python Modules
Classifier: Topic :: Scientific/Engineering :: GIS
Classifier: Topic :: Scientific/Engineering :: Information Analysis
Classifier: Topic :: Database
License-File: LICENSE
Requires-Dist: xlrd
Requires-Dist: future
Requires-Dist: kaggle
Requires-Dist: argcomplete
Requires-Dist: tqdm
Requires-Dist: requests
Requires-Dist: pandas
Requires-Dist: h5py
Requires-Dist: Pillow
